ragtime_cli-0.2.17.dist-info/licenses/LICENSE
src/__init__.py
src/cli.py
src/config.py
src/db.py
src/feedback.py
src/mcp_server.py
src/memory.py
src/commands/audit.md
src/commands/create-pr.md
src/commands/generate-docs.md
src/commands/handoff.md
src/commands/import-docs.md
src/commands/pr-graduate.md
src/commands/recall.md
src/commands/remember.md
src/commands/save.md
src/commands/start.md
src/indexers/__init__.py
src/indexers/code.py
src/indexers/docs.py
ragtime_cli-0.2.17.dist-info/METADATA
ragtime_cli-0.2.17.dist-info/WHEEL
ragtime_cli-0.2.17.dist-info/entry_points.txt
ragtime_cli-0.2.17.dist-info/top_level.txt
ragtime_cli-0.2.17.dist-info/RECORD
