Metadata-Version: 2.4
Name: ragtime-cli
Version: 0.2.17
Summary: Local-first memory and RAG system for Claude Code - semantic search over code, docs, and team knowledge
Author-email: Bret Martineau <bretwardjames@gmail.com>
License-Expression: MIT
Project-URL: Homepage, https://github.com/bretwardjames/ragtime
Project-URL: Repository, https://github.com/bretwardjames/ragtime
Project-URL: Issues, https://github.com/bretwardjames/ragtime/issues
Keywords: claude,rag,memory,mcp,ai,llm,semantic-search,vector-database
Classifier: Development Status :: 4 - Beta
Classifier: Environment :: Console
Classifier: Intended Audience :: Developers
Classifier: Programming Language :: Python :: 3
Classifier: Programming Language :: Python :: 3.11
Classifier: Programming Language :: Python :: 3.12
Classifier: Programming Language :: Python :: 3.13
Classifier: Topic :: Software Development :: Documentation
Classifier: Topic :: Text Processing :: Indexing
Requires-Python: >=3.11
License-File: LICENSE
Requires-Dist: chromadb>=0.4.0
Requires-Dist: pyyaml>=6.0
Requires-Dist: click>=8.0
Provides-Extra: dev
Requires-Dist: pytest>=8.0; extra == "dev"
Requires-Dist: ruff>=0.1.0; extra == "dev"
Dynamic: license-file
